README.md
setup.py
module/__init__.py
module/module.py
py_slack/__init__.py
py_slack/send_hook.py
py_slack.egg-info/PKG-INFO
py_slack.egg-info/SOURCES.txt
py_slack.egg-info/dependency_links.txt
py_slack.egg-info/requires.txt
py_slack.egg-info/top_level.txt