Metadata-Version: 2.1
Name: py-slack
Version: 0.0.0
Summary: Basic webhook messaging, want to add bot interactivy next
Home-page: https://github.com/deadlift1226/py_slack
Author: Dane Morgan
Author-email: danemorgan91@gmail.com
License: UNKNOWN
Platform: UNKNOWN
Classifier: Programming Language :: Python :: 3
Classifier: License :: OSI Approved :: MIT License
Classifier: Operating System :: OS Independent
